poisson/__init__.py
poisson/main.py
poisson/pypoissonMG.cp38-win_amd64.pyd
poisson-0.3.dist-info/LICENSE
poisson-0.3.dist-info/METADATA
poisson-0.3.dist-info/WHEEL
poisson-0.3.dist-info/top_level.txt
poisson-0.3.dist-info/RECORD
