Metadata-Version: 2.1
Name: poisson
Version: 0.3
Summary: Equation de Poisson
Home-page: http://www.f-legrand.fr
Author: Frederic Legrand
Author-email: fredlegr@club-internet.fr
License: CeCILL
Platform: UNKNOWN
